setup.py
wekit/__init__.py
wekit/messenger.py
wekit.egg-info/PKG-INFO
wekit.egg-info/SOURCES.txt
wekit.egg-info/dependency_links.txt
wekit.egg-info/top_level.txt