Metadata-Version: 1.0
Name: wekit
Version: 0.0.1
Summary: Weteam Python SDK
Home-page: https://coding.net/u/jeff/p/wekit/git
Author: jeff kit
Author-email: bbmyth@gmail.com
License: UNKNOWN
Platform: UNKNOWN
